saltext/vmware/__init__.py
saltext/vmware/loader.py
saltext/vmware/version.py
saltext/vmware/config/schemas/esxcluster.py
saltext/vmware/config/schemas/esxdatacenter.py
saltext/vmware/config/schemas/esxi.py
saltext/vmware/config/schemas/esxvm.py
saltext/vmware/config/schemas/vcenter.py
saltext/vmware/grains/esxi.py
saltext/vmware/modules/cluster.py
saltext/vmware/modules/cluster_drs.py
saltext/vmware/modules/cluster_ha.py
saltext/vmware/modules/coredump.py
saltext/vmware/modules/datacenter.py
saltext/vmware/modules/datastore.py
saltext/vmware/modules/disk.py
saltext/vmware/modules/dvportgroup.py
saltext/vmware/modules/dvs.py
saltext/vmware/modules/dvswitch.py
saltext/vmware/modules/esxi.py
saltext/vmware/modules/extra.py
saltext/vmware/modules/firewall.py
saltext/vmware/modules/folder.py
saltext/vmware/modules/info.py
saltext/vmware/modules/license.py
saltext/vmware/modules/license_mgr.py
saltext/vmware/modules/nsxt_compute_manager.py
saltext/vmware/modules/nsxt_ip_blocks.py
saltext/vmware/modules/nsxt_ip_pools.py
saltext/vmware/modules/nsxt_license.py
saltext/vmware/modules/nsxt_manager.py
saltext/vmware/modules/nsxt_policy_segment.py
saltext/vmware/modules/nsxt_policy_tier0.py
saltext/vmware/modules/nsxt_policy_tier1.py
saltext/vmware/modules/nsxt_transport_node.py
saltext/vmware/modules/nsxt_transport_node_profiles.py
saltext/vmware/modules/nsxt_transport_zone.py
saltext/vmware/modules/nsxt_uplink_profiles.py
saltext/vmware/modules/ntp.py
saltext/vmware/modules/service.py
saltext/vmware/modules/ssl_adapter.py
saltext/vmware/modules/storage_policies.py
saltext/vmware/modules/syslog.py
saltext/vmware/modules/tag.py
saltext/vmware/modules/vcenter.py
saltext/vmware/modules/vm.py
saltext/vmware/modules/vmc_dhcp_profiles.py
saltext/vmware/modules/vmc_direct_connect.py
saltext/vmware/modules/vmc_distributed_firewall_rules.py
saltext/vmware/modules/vmc_dns_forwarder.py
saltext/vmware/modules/vmc_nat_rules.py
saltext/vmware/modules/vmc_networks.py
saltext.vmware-23.6.29.0rc1.dist-info/LICENSE
saltext.vmware-23.6.29.0rc1.dist-info/METADATA
saltext.vmware-23.6.29.0rc1.dist-info/NOTICE.txt
saltext.vmware-23.6.29.0rc1.dist-info/WHEEL
saltext.vmware-23.6.29.0rc1.dist-info/entry_points.txt
saltext.vmware-23.6.29.0rc1.dist-info/top_level.txt
saltext.vmware-23.6.29.0rc1.dist-info/RECORD
